select_git_author/__init__.py
select_git_author/cli.py
select_git_author-0.2.3.dist-info/WHEEL
select_git_author-0.2.3.dist-info/entry_points.txt
select_git_author-0.2.3.dist-info/METADATA
select_git_author-0.2.3.dist-info/RECORD
