Metadata-Version: 2.3
Name: select-git-author
Version: 0.2.3
Summary: Interactively select the author for the next git commit
Keywords: cli,git
Author: Markus Grotz
Author-email: Markus Grotz <grotz@uw.edu>
License: MIT License
Classifier: Programming Language :: Python :: 3
Classifier: License :: OSI Approved :: MIT License
Classifier: Operating System :: OS Independent
Requires-Dist: click-prompt>=0.6.2
Requires-Python: >=3.7
